budosystems/py.typed
budosystems/dsl/__init__.py
budosystems/dsl/command-sample-1.txt
budosystems/dsl/model-sample-1.txt
budosystems/dsl/py.typed
budosystems/dsl/query-sample-1.txt
budosystems/events/__init__.py
budosystems/events/base.py
budosystems/events/collections.py
budosystems/events/message_bus.py
budosystems/events/py.typed
budosystems/models/__init__.py
budosystems/models/calendar.py
budosystems/models/contact.py
budosystems/models/core.py
budosystems/models/meta.py
budosystems/models/people.py
budosystems/models/program.py
budosystems/models/py.typed
budosystems/models/retail.py
budosystems/models/style.py
budosystems/models/validation.py
budosystems/services/__init__.py
budosystems/services/operations.py
budosystems/services/py.typed
budosystems/storage/__init__.py
budosystems/storage/dict_repository.py
budosystems/storage/mapper.py
budosystems/storage/py.typed
budosystems/storage/query.py
budosystems/storage/repository.py
budosystems/typehints/__init__.py
budosystems/typehints/py.typed
budosystems/utils/__init__.py
budosystems/utils/_version.py
budosystems/utils/py.typed
budosystems/xtra/namespace.txt
budosystems_core-0.3.6.dist-info/LICENCE.txt
budosystems_core-0.3.6.dist-info/METADATA
budosystems_core-0.3.6.dist-info/WHEEL
budosystems_core-0.3.6.dist-info/top_level.txt
budosystems_core-0.3.6.dist-info/RECORD
